dfn/__init__.py
dfn/__main__.py
dfn/util.py
dfn-1.5.0.dist-info/METADATA
dfn-1.5.0.dist-info/WHEEL
dfn-1.5.0.dist-info/top_level.txt
dfn-1.5.0.dist-info/RECORD
