Metadata-Version: 2.1
Name: dfn
Version: 1.5.0
Summary: download_from_nas
Author: yifei.gao
Author-email: yifei.gao@sophgo.com
Requires-Dist: requests
Requires-Dist: tqdm
